pumpfun_sdk/__init__.py
pumpfun_sdk/analytics.py
pumpfun_sdk/client.py
pumpfun_sdk/config.py
pumpfun_sdk/idl.py
pumpfun_sdk/pump_curve.py
pumpfun_sdk/transaction.py
pumpfun_sdk/usecases/token.py
pumpfun_sdk/usecases/user.py
pumpfun_sdk/utils.py
pumpfun_sdk-0.1.0.dist-info/LICENSE
pumpfun_sdk-0.1.0.dist-info/METADATA
pumpfun_sdk-0.1.0.dist-info/WHEEL
pumpfun_sdk-0.1.0.dist-info/RECORD
