Metadata-Version: 2.1
Name: pumpfun-sdk
Version: 0.1.0
Summary: Python SDK for interacting with the Pump.fun protocol on Solana blockchain
Home-page: https://github.com/gendev1/pumpfun-sdk
License: MIT
Keywords: solana,blockchain,pump.fun,trading,sdk
Author: Your Name
Author-email: your.email@example.com
Requires-Python: >=3.8,<4.0
Classifier: Development Status :: 4 - Beta
Classifier: Intended Audience :: Developers
Classifier: License :: OSI Approved :: MIT License
Classifier: Programming Language :: Python :: 3
Classifier: Programming Language :: Python :: 3.8
Classifier: Programming Language :: Python :: 3.9
Classifier: Programming Language :: Python :: 3.10
Classifier: Programming Language :: Python :: 3.11
Classifier: Topic :: Software Development :: Libraries :: Python Modules
Requires-Dist: aiohttp (>=3.8.0,<4.0.0)
Requires-Dist: asyncio (>=3.4.3,<4.0.0)
Requires-Dist: construct (>=2.10.0,<3.0.0)
Requires-Dist: solders (>=0.19.0,<0.20.0)
Requires-Dist: websockets (>=10.0,<11.0)
Project-URL: Documentation, https://github.com/gendev1/pumpfun-sdk#readme
Project-URL: Repository, https://github.com/gendev1/pumpfun-sdk
